pymatreader/__init__.py
pymatreader/_version.py
pymatreader/pymatreader.py
pymatreader/utils.py
pymatreader-0.0.32.dist-info/LICENSE
pymatreader-0.0.32.dist-info/METADATA
pymatreader-0.0.32.dist-info/WHEEL
pymatreader-0.0.32.dist-info/top_level.txt
pymatreader-0.0.32.dist-info/RECORD
