Metadata-Version: 2.1
Name: pymatreader
Version: 0.0.32
Summary: Convenient reader for Matlab mat files
Home-page: https://gitlab.com/obob/pymatreader
Author: Dirk Gütlin & Thomas Hartmann
Author-email: thomas.hartmann@th-ht.de
License: BSD (2 clause)
Keywords: Matlab HDF5 import
Classifier: Development Status :: 4 - Beta
Classifier: Intended Audience :: Science/Research
Classifier: License :: OSI Approved :: BSD License
Classifier: Operating System :: OS Independent
Classifier: Programming Language :: Python
License-File: LICENSE
